distilclient/__init__.py
distilclient/base.py
distilclient/cli.py
distilclient/client.py
distilclient/exc.py
distilclient/exceptions.py
distilclient/i18n.py
distilclient/shell.py
distilclient/utils.py
distilclient/version.py
distilclient/common/__init__.py
distilclient/common/cliutils.py
distilclient/common/httpclient.py
distilclient/common/utils.py
distilclient/common/apiclient/__init__.py
distilclient/common/apiclient/auth.py
distilclient/common/apiclient/base.py
distilclient/common/apiclient/client.py
distilclient/common/apiclient/exceptions.py
distilclient/common/apiclient/fake_client.py
distilclient/common/apiclient/utils.py
distilclient/tests/__init__.py
distilclient/tests/functional/__init__.py
distilclient/tests/unit/__init__.py
distilclient/tests/unit/fakes.py
distilclient/tests/unit/test_base.py
distilclient/tests/unit/test_client.py
distilclient/tests/unit/utils.py
distilclient/tests/unit/v1/__init__.py
distilclient/tests/unit/v1/test_client.py
distilclient/tests/unit/v2/__init__.py
distilclient/tests/unit/v2/fake_clients.py
distilclient/tests/unit/v2/fakes.py
distilclient/tests/unit/v2/test_client.py
distilclient/tests/unit/v2/test_credits.py
distilclient/tests/unit/v2/test_health.py
distilclient/tests/unit/v2/test_invoices.py
distilclient/tests/unit/v2/test_measurements.py
distilclient/tests/unit/v2/test_products.py
distilclient/tests/unit/v2/test_quotations.py
distilclient/v1/__init__.py
distilclient/v1/client.py
distilclient/v2/__init__.py
distilclient/v2/cli.py
distilclient/v2/client.py
distilclient/v2/credits.py
distilclient/v2/health.py
distilclient/v2/invoices.py
distilclient/v2/measurements.py
distilclient/v2/products.py
distilclient/v2/quotations.py
python_distilclient-0.4.0.dist-info/METADATA
python_distilclient-0.4.0.dist-info/RECORD
python_distilclient-0.4.0.dist-info/WHEEL
python_distilclient-0.4.0.dist-info/entry_points.txt
python_distilclient-0.4.0.dist-info/pbr.json
python_distilclient-0.4.0.dist-info/top_level.txt
