Metadata-Version: 2.1
Name: python-distilclient
Version: 0.4.0
Summary: Client library for Catalyst Cloud Rating API
Home-page: http://www.catalyst.net.nz/
Author: Catalyst IT Cloud team
Author-email: cloud@catalyst.net.nz
License: Apache License, Version 2.0
Platform: UNKNOWN
Classifier: Development Status :: 5 - Production/Stable
Classifier: Environment :: Console
Classifier: Environment :: OpenStack
Classifier: Intended Audience :: Information Technology
Classifier: Intended Audience :: Developers
Classifier: Intended Audience :: System Administrators
Classifier: License :: OSI Approved :: Apache Software License
Classifier: Operating System :: POSIX :: Linux
Classifier: Programming Language :: Python
Classifier: Programming Language :: Python :: 2.7
Requires-Dist: six (>=1.9.0)
Requires-Dist: pbr (>=1.6)
Requires-Dist: python-keystoneclient (!=1.8.0,!=2.1.0,>=1.7.0)
Requires-Dist: osc-lib (>=1.7.0)
Requires-Dist: python-openstackclient (>=3.12.0)
Requires-Dist: oslo.log (>=3.30.0)
Requires-Dist: debtcollector (>=1.2.0)
